{
  "fixedSchedule": [],
  "spontaneousEntries": [
    {
      "linie": "S2",
      "ziel": "haha",
      "plan": "12:12",
      "actual": "12:30",
      "dauer": 120,
      "zwischenhalte": [],
      "canceled": false,
      "date": "2026-02-09",
      "_uniqueId": "train_ifgpq7b47_1770630241711",
      "plannedDate": "2026-02-09"
    },
    {
      "linie": "S7",
      "ziel": "Tesla",
      "plan": "12:00",
      "actual": "12:00",
      "dauer": 100,
      "zwischenhalte": [],
      "canceled": false,
      "date": "2026-02-09",
      "_uniqueId": "train_j7w5o2ruz_1770633766020",
      "plannedDate": "2026-02-09"
    },
    {
      "linie": "S4",
      "ziel": "Hildesheim",
      "plan": "",
      "dauer": 6,
      "zwischenhalte": [
        ""
      ],
      "canceled": false,
      "date": "2026-02-09",
      "_uniqueId": "train_hmorb8u8y_1770644986840",
      "plannedDate": "2026-02-09"
    },
    {
      "linie": "S8",
      "ziel": "Dörverden",
      "plan": "11:00",
      "actual": "22:10",
      "dauer": 30,
      "zwischenhalte": [
        ""
      ],
      "canceled": false,
      "date": "2026-02-09",
      "_uniqueId": "train_0vwezc3lz_1770657976017",
      "plannedDate": "2026-02-09"
    },
    {
      "linie": "S60",
      "ziel": "ExPhys",
      "plan": "22:00",
      "dauer": 120,
      "zwischenhalte": [],
      "canceled": false,
      "date": "2026-02-09",
      "_uniqueId": "train_12isrcun4_1770667893919",
      "actual": "00:00",
      "plannedDate": "2026-02-09"
    },
    {
      "linie": "S5",
      "ziel": "Test",
      "plan": "",
      "dauer": 0,
      "zwischenhalte": [
        "regerger"
      ],
      "canceled": false,
      "date": "2026-02-10",
      "_uniqueId": "train_j4v6miua4_1770757757554",
      "plannedDate": "2026-02-10"
    },
    {
      "linie": "S9",
      "ziel": "Flughafen BER",
      "plan": "10:10",
      "actual": "22:40",
      "dauer": 1000,
      "zwischenhalte": [],
      "canceled": false,
      "date": "2026-02-10",
      "_uniqueId": "train_7akihsmjj_1770757835431",
      "plannedDate": "2026-02-10"
    },
    {
      "linie": "S5",
      "ziel": "Makelhaf",
      "plan": "22:15",
      "actual": "01:09",
      "dauer": 101,
      "zwischenhalte": [],
      "canceled": false,
      "date": "2026-02-10",
      "_uniqueId": "train_4z10t28u0_1770757867158",
      "plannedDate": "2026-02-10"
    },
    {
      "linie": "RE1",
      "ziel": "Bremen Hbf",
      "plan": "23:30",
      "dauer": 0,
      "zwischenhalte": [],
      "canceled": false,
      "date": "2026-02-10",
      "_uniqueId": "train_174qx45a5_1770762440386",
      "actual": "23:30",
      "plannedDate": "2026-02-10"
    },
    {
      "linie": "S6",
      "ziel": "",
      "plan": "",
      "dauer": 0,
      "zwischenhalte": [],
      "canceled": false,
      "date": "2026-02-11",
      "_uniqueId": "train_dn34v766t_1770828411336",
      "plannedDate": "2026-02-11"
    },
    {
      "_uniqueId": "train_az2z5swjk_1770833608343",
      "linie": "s1",
      "ziel": "k",
      "plan": "",
      "actual": "18:22",
      "dauer": 0,
      "zwischenhalte": [],
      "canceled": false,
      "date": "2026-02-11",
      "projectId": null,
      "done": false,
      "plannedDate": "2026-02-11"
    },
    {
      "_uniqueId": "train_gxf3w3jpf_1770833616099",
      "linie": "s1",
      "ziel": "hih",
      "plan": "",
      "actual": "",
      "dauer": 0,
      "zwischenhalte": [],
      "canceled": false,
      "date": "2026-02-11",
      "projectId": "project_66lc1ni1h_1770833599291",
      "done": false,
      "plannedDate": "2026-02-11"
    },
    {
      "_uniqueId": "train_3yp57juqg_1770833618145",
      "linie": "s1",
      "ziel": "thrthrh",
      "plan": "",
      "actual": "",
      "dauer": 0,
      "zwischenhalte": [],
      "canceled": false,
      "date": "2026-02-11",
      "projectId": "project_66lc1ni1h_1770833599291",
      "done": false,
      "plannedDate": "2026-02-11"
    },
    {
      "_uniqueId": "train_6oe5j5mtl_1770834807988",
      "linie": "s45",
      "ziel": "Fachschaftssitzung",
      "plan": "",
      "actual": "",
      "dauer": 0,
      "zwischenhalte": [],
      "canceled": false,
      "date": "2026-02-21",
      "projectId": null,
      "done": false,
      "plannedDate": "2026-02-11"
    },
    {
      "_uniqueId": "train_xn1xipauk_1770839259326",
      "linie": "s1",
      "ziel": "Hallo",
      "plan": "",
      "actual": "",
      "dauer": 0,
      "zwischenhalte": [],
      "canceled": false,
      "date": "2026-02-11",
      "projectId": null,
      "done": false,
      "plannedDate": "2026-02-11"
    },
    {
      "linie": "S5",
      "ziel": "This project should have start date 15.02",
      "plan": "10:10",
      "actual": "10:10",
      "dauer": 100,
      "zwischenhalte": [],
      "canceled": false,
      "date": "2026-02-20",
      "plannedDate": "2026-02-15",
      "_uniqueId": "train_pc2gd9moj_1770839422698",
      "projectId": "project_9ao8r6p2f_1770834514727"
    },
    {
      "linie": "S6",
      "ziel": "Dont die",
      "plan": "12:12",
      "actual": "21:30",
      "dauer": 0,
      "zwischenhalte": [],
      "canceled": false,
      "date": "2026-02-11",
      "plannedDate": "2026-02-11",
      "_uniqueId": "train_yyqs3ad6d_1770839947706",
      "done": false
    },
    {
      "linie": "s45",
      "ziel": "Hallo",
      "plan": "10:10",
      "dauer": 10,
      "zwischenhalte": [],
      "canceled": false,
      "date": "2026-02-11",
      "plannedDate": "2026-02-11",
      "_uniqueId": "train_xd3g9ibpl_1770839965316",
      "projectId": null,
      "done": false,
      "actual": "10:10"
    },
    {
      "linie": "s6",
      "ziel": "Help me",
      "plan": "10:00",
      "dauer": 10000,
      "zwischenhalte": [],
      "canceled": true,
      "date": "2026-02-11",
      "plannedDate": "2026-02-11",
      "_uniqueId": "train_97dm641on_1770839979081",
      "projectId": "project_9ao8r6p2f_1770834514727",
      "done": false,
      "actual": "10:00"
    },
    {
      "linie": "S5",
      "ziel": "HBF",
      "plan": "10:10",
      "actual": "10:10",
      "dauer": 100,
      "zwischenhalte": [],
      "canceled": false,
      "date": "2026-02-11",
      "plannedDate": "2026-02-11",
      "_uniqueId": "train_xi1qpgvok_1770840296327",
      "done": false
    },
    {
      "linie": "S5",
      "ziel": "HBF",
      "plan": "23:59",
      "actual": "23:59",
      "dauer": 100,
      "zwischenhalte": [],
      "canceled": false,
      "date": "2026-02-11",
      "plannedDate": "2026-02-11",
      "_uniqueId": "train_sqrnobsxu_1770840343442",
      "done": false,
      "projectId": "project_9ao8r6p2f_1770834514727"
    },
    {
      "linie": "s45",
      "ziel": "From project editor",
      "plan": "",
      "dauer": 0,
      "zwischenhalte": [],
      "canceled": false,
      "date": "2026-02-11",
      "plannedDate": "2026-02-11",
      "_uniqueId": "train_a1kr0e1k5_1770840389527",
      "projectId": null,
      "done": false
    },
    {
      "linie": "s45",
      "ziel": "This one should have a date (me)",
      "plan": "09:59",
      "dauer": 100,
      "zwischenhalte": [],
      "canceled": false,
      "date": "2026-02-15",
      "plannedDate": "2026-02-15",
      "_uniqueId": "train_s9myexg2x_1770841100470",
      "projectId": "project_9ao8r6p2f_1770834514727",
      "done": false,
      "actual": "09:59"
    },
    {
      "linie": "s45",
      "ziel": "This one too",
      "plan": "20:10",
      "dauer": 1000,
      "zwischenhalte": [],
      "canceled": false,
      "date": "2026-02-14",
      "plannedDate": "2026-02-14",
      "_uniqueId": "train_bnh95gjot_1770841158568",
      "projectId": "project_9ao8r6p2f_1770834514727",
      "done": false,
      "actual": "20:10"
    },
    {
      "linie": "s25",
      "ziel": "Hello",
      "plan": "10:10",
      "dauer": 100,
      "zwischenhalte": [],
      "canceled": false,
      "date": "2026-02-11",
      "plannedDate": "2026-02-11",
      "_uniqueId": "train_gvzdn87uy_1770841534759",
      "projectId": null,
      "done": false,
      "actual": "10:10"
    },
    {
      "linie": "s25",
      "ziel": "Die",
      "plan": "21:29",
      "dauer": 20,
      "zwischenhalte": [],
      "canceled": false,
      "date": "2026-02-13",
      "plannedDate": "2026-02-12",
      "_uniqueId": "train_viqt1p9ea_1770841596692",
      "projectId": "project_9ao8r6p2f_1770834514727",
      "done": false,
      "actual": "21:29"
    },
    {
      "linie": "S25",
      "ziel": "This one shouldnt have a planned time i think",
      "plan": "20:20",
      "actual": "20:20",
      "dauer": 100,
      "zwischenhalte": [],
      "canceled": false,
      "date": "2026-02-11",
      "plannedDate": "2026-02-11",
      "_uniqueId": "train_ve24cgaco_1770841648786",
      "done": false,
      "projectId": "project_9ao8r6p2f_1770834514727"
    },
    {
      "linie": "S7",
      "ziel": "This one should have 11.2 as date tbh",
      "plan": "10:10",
      "actual": "20:20",
      "dauer": 10000,
      "zwischenhalte": [],
      "canceled": true,
      "date": "2026-02-12",
      "plannedDate": "2026-02-11",
      "_uniqueId": "train_4h8xcccdu_1770841821876",
      "done": false,
      "projectId": "project_9ao8r6p2f_1770834514727"
    },
    {
      "linie": "1",
      "ziel": "And this one should have planned date as 20.2, and actual date 22.2",
      "plan": "10:10",
      "actual": "10:10",
      "dauer": 100,
      "zwischenhalte": [],
      "canceled": false,
      "date": "2026-02-22",
      "plannedDate": "2026-02-20",
      "_uniqueId": "train_fp0cdu3yl_1770841848526",
      "done": false,
      "projectId": "project_9ao8r6p2f_1770834514727"
    },
    {
      "linie": "S1",
      "ziel": "perfect",
      "plan": "",
      "dauer": 0,
      "zwischenhalte": [],
      "canceled": false,
      "date": "2026-02-23",
      "plannedDate": "2026-02-11",
      "_uniqueId": "train_9gx7pyywb_1770841893212",
      "projectId": null,
      "done": false
    },
    {
      "linie": "S6",
      "ziel": "However this one shouldnt assume",
      "plan": "12:20",
      "dauer": 10000,
      "zwischenhalte": [],
      "canceled": false,
      "date": "2026-02-11",
      "plannedDate": "2026-02-11",
      "_uniqueId": "train_1y1bbm0ff_1770842511778",
      "projectId": "project_9ao8r6p2f_1770834514727",
      "done": false,
      "actual": "20:20"
    },
    {
      "linie": "S6",
      "ziel": "HAHA",
      "plan": "11:11",
      "dauer": 0,
      "zwischenhalte": [],
      "canceled": false,
      "date": "2026-02-10",
      "plannedDate": "2026-02-10",
      "_uniqueId": "train_vtjnwyopo_1770848930842",
      "projectId": null,
      "done": false,
      "actual": "11:11"
    },
    {
      "linie": "S1",
      "ziel": "Omg hiiii",
      "plan": "10:10",
      "actual": "20:00",
      "dauer": 100,
      "zwischenhalte": [],
      "canceled": false,
      "date": "2026-02-12",
      "plannedDate": "2026-02-12",
      "_uniqueId": "train_6iiamdshx_1770913549521",
      "done": false,
      "projectId": "project_9ao8r6p2f_1770834514727"
    },
    {
      "linie": "S5",
      "ziel": "Slay",
      "plan": "10:10",
      "dauer": 100,
      "zwischenhalte": [],
      "canceled": true,
      "date": "2026-02-13",
      "plannedDate": "2026-02-12",
      "_uniqueId": "train_7c7ms7pwl_1770914722464",
      "projectId": "project_6oej3qm4n_1770914709412",
      "done": false,
      "actual": "10:10"
    },
    {
      "linie": "S1",
      "ziel": "Hallo",
      "plan": "10:10",
      "dauer": 0,
      "zwischenhalte": [],
      "canceled": false,
      "date": "2026-02-12",
      "plannedDate": "2026-02-12",
      "_uniqueId": "train_zqr0sxk82_1770914862487",
      "done": false,
      "actual": "10:10"
    },
    {
      "linie": "S3",
      "ziel": "my name is pink and its nice to meet you",
      "plan": "",
      "dauer": 0,
      "zwischenhalte": [],
      "canceled": false,
      "date": "",
      "plannedDate": "",
      "_uniqueId": "train_qypzze0r0_1770925377786",
      "projectId": "project_9ao8r6p2f_1770834514727",
      "tags": [
        "todo-done"
      ],
      "todoChecked": false
    },
    {
      "linie": "S3",
      "ziel": "youre recommended to me by some people",
      "plan": "",
      "dauer": 0,
      "zwischenhalte": [
        "Hi"
      ],
      "canceled": false,
      "date": "2026-02-12",
      "plannedDate": "2026-02-12",
      "_uniqueId": "train_qkudc9klt_1770925387983",
      "projectId": "project_9ao8r6p2f_1770834514727",
      "tags": [
        "todo-done"
      ],
      "todoChecked": false
    },
    {
      "linie": "S3",
      "ziel": "hey oooooh is this illegal",
      "plan": "",
      "dauer": 0,
      "zwischenhalte": [],
      "canceled": false,
      "date": "2026-02-13",
      "plannedDate": "2026-02-13",
      "_uniqueId": "train_85bd79wvx_1770925395898",
      "projectId": "project_9ao8r6p2f_1770834514727",
      "tags": [
        "todo-done"
      ],
      "todoChecked": false
    },
    {
      "linie": "S7",
      "ziel": "hey ooooh it feels illegal",
      "plan": "",
      "dauer": 0,
      "zwischenhalte": [],
      "canceled": false,
      "date": "",
      "plannedDate": "",
      "_uniqueId": "train_7u31xfcyy_1770927285381",
      "projectId": "project_9ao8r6p2f_1770834514727",
      "tags": [
        "todo-done"
      ],
      "todoChecked": false
    },
    {
      "linie": "S7",
      "ziel": "i've suffered quite a few times with paranoia",
      "plan": "",
      "dauer": 0,
      "zwischenhalte": [],
      "canceled": false,
      "date": "",
      "plannedDate": "",
      "_uniqueId": "train_ggp694tdn_1770927307417",
      "projectId": "project_9ao8r6p2f_1770834514727",
      "tags": [
        "todo-done"
      ],
      "todoChecked": false
    },
    {
      "linie": "S7",
      "ziel": "oh whats your name i dont know what i should call ya",
      "plan": "",
      "dauer": 0,
      "zwischenhalte": [],
      "canceled": false,
      "date": "",
      "plannedDate": "",
      "_uniqueId": "train_qh4kb00xz_1770927316197",
      "projectId": "project_9ao8r6p2f_1770834514727",
      "tags": [
        "todo-done"
      ],
      "todoChecked": false
    },
    {
      "linie": "S7",
      "ziel": "hell oooh heres 20 for ya",
      "plan": "",
      "dauer": 0,
      "zwischenhalte": [],
      "canceled": false,
      "date": "",
      "plannedDate": "",
      "_uniqueId": "train_72fcoqzrm_1770927321914",
      "projectId": "project_9ao8r6p2f_1770834514727",
      "tags": [
        "todo-done"
      ],
      "todoChecked": false
    },
    {
      "linie": "S7",
      "ziel": "hey ooj we can hide around the corner",
      "plan": "",
      "dauer": 0,
      "zwischenhalte": [],
      "canceled": false,
      "date": "",
      "plannedDate": "",
      "_uniqueId": "train_bsjjzn1dk_1770927331605",
      "projectId": "project_9ao8r6p2f_1770834514727",
      "tags": [
        "todo-done"
      ],
      "todoChecked": true
    },
    {
      "linie": "S7",
      "ziel": "omg is this reallllll",
      "plan": "",
      "dauer": 0,
      "zwischenhalte": [],
      "canceled": false,
      "date": "",
      "plannedDate": "",
      "_uniqueId": "train_l24wwnrhj_1770930234312",
      "projectId": "project_9ao8r6p2f_1770834514727",
      "tags": [
        "todo-done"
      ],
      "todoChecked": false
    },
    {
      "linie": "S7",
      "ziel": "this is so fun ykkkkk",
      "plan": "",
      "dauer": 0,
      "zwischenhalte": [],
      "canceled": false,
      "date": "",
      "plannedDate": "",
      "_uniqueId": "train_31n9uzo9n_1770930239067",
      "projectId": "project_9ao8r6p2f_1770834514727",
      "tags": [
        "todo-done"
      ],
      "todoChecked": false
    },
    {
      "linie": "S7",
      "ziel": "yall im so good",
      "plan": "",
      "dauer": 0,
      "zwischenhalte": [],
      "canceled": false,
      "date": "",
      "plannedDate": "",
      "_uniqueId": "train_tt0cc08v3_1770930705168",
      "projectId": "project_9ao8r6p2f_1770834514727",
      "tags": [
        "todo-done"
      ],
      "todoChecked": false
    },
    {
      "linie": "S7",
      "ziel": "at making time tables and stuffs",
      "plan": "",
      "dauer": 0,
      "zwischenhalte": [],
      "canceled": false,
      "date": "",
      "plannedDate": "",
      "_uniqueId": "train_ds18xl852_1770930710658",
      "projectId": "project_9ao8r6p2f_1770834514727",
      "tags": [
        "todo-done"
      ],
      "todoChecked": false
    },
    {
      "linie": "S7",
      "ziel": "omg yay",
      "plan": "",
      "dauer": 0,
      "zwischenhalte": [],
      "canceled": false,
      "date": "",
      "plannedDate": "",
      "_uniqueId": "train_d3mckicgr_1770930713310",
      "projectId": "project_9ao8r6p2f_1770834514727",
      "tags": [
        "todo-done"
      ],
      "todoChecked": false
    },
    {
      "linie": "S7",
      "ziel": "mom look at me im flying",
      "plan": "",
      "dauer": 0,
      "zwischenhalte": [],
      "canceled": false,
      "date": "",
      "plannedDate": "",
      "_uniqueId": "train_d69gbhrel_1770930717678",
      "projectId": "project_9ao8r6p2f_1770834514727",
      "tags": [
        "todo-done"
      ],
      "todoChecked": true
    },
    {
      "linie": "S7",
      "ziel": "lol help all my todos are gone",
      "plan": "",
      "dauer": 0,
      "zwischenhalte": [],
      "canceled": false,
      "date": "",
      "plannedDate": "",
      "_uniqueId": "train_1c34qso0t_1770933468937",
      "projectId": "project_9ao8r6p2f_1770834514727",
      "type": "todo",
      "todoChecked": true
    },
    {
      "linie": "S7",
      "ziel": "sf",
      "plan": "",
      "dauer": 0,
      "zwischenhalte": [],
      "canceled": false,
      "date": "",
      "plannedDate": "",
      "_uniqueId": "train_nstagtrcb_1770934295231",
      "projectId": "project_9ao8r6p2f_1770834514727",
      "type": "todo",
      "todoChecked": true
    },
    {
      "linie": "S7",
      "ziel": "f",
      "plan": "",
      "dauer": 0,
      "zwischenhalte": [],
      "canceled": false,
      "date": "",
      "plannedDate": "",
      "_uniqueId": "train_u3sp4efra_1770934295540",
      "projectId": "project_9ao8r6p2f_1770834514727",
      "type": "todo",
      "todoChecked": true
    },
    {
      "linie": "S7",
      "ziel": "h",
      "plan": "",
      "dauer": 0,
      "zwischenhalte": [],
      "canceled": false,
      "date": "",
      "plannedDate": "",
      "_uniqueId": "train_1kayviazt_1770934295810",
      "projectId": "project_9ao8r6p2f_1770834514727",
      "type": "todo",
      "todoChecked": true
    },
    {
      "linie": "S7",
      "ziel": "dt",
      "plan": "",
      "dauer": 0,
      "zwischenhalte": [],
      "canceled": false,
      "date": "",
      "plannedDate": "",
      "_uniqueId": "train_wm04i9r9s_1770934296098",
      "projectId": "project_9ao8r6p2f_1770834514727",
      "type": "todo",
      "todoChecked": true
    },
    {
      "linie": "S7",
      "ziel": "th",
      "plan": "",
      "dauer": 0,
      "zwischenhalte": [],
      "canceled": false,
      "date": "",
      "plannedDate": "",
      "_uniqueId": "train_pv9uhgkgh_1770934296377",
      "projectId": "project_9ao8r6p2f_1770834514727",
      "type": "todo",
      "todoChecked": true
    },
    {
      "linie": "S7",
      "ziel": "fzt",
      "plan": "",
      "dauer": 0,
      "zwischenhalte": [],
      "canceled": false,
      "date": "",
      "plannedDate": "",
      "_uniqueId": "train_498p1b6b7_1770934296660",
      "projectId": "project_9ao8r6p2f_1770834514727",
      "type": "todo",
      "todoChecked": true
    },
    {
      "linie": "S7",
      "ziel": "h",
      "plan": "",
      "dauer": 0,
      "zwischenhalte": [],
      "canceled": false,
      "date": "",
      "plannedDate": "",
      "_uniqueId": "train_0wkj17y8m_1770934296936",
      "projectId": "project_9ao8r6p2f_1770834514727",
      "type": "todo",
      "todoChecked": true
    },
    {
      "linie": "S7",
      "ziel": "ert",
      "plan": "",
      "dauer": 0,
      "zwischenhalte": [],
      "canceled": false,
      "date": "",
      "plannedDate": "",
      "_uniqueId": "train_q7voja4jv_1770934297221",
      "projectId": "project_9ao8r6p2f_1770834514727",
      "type": "todo",
      "todoChecked": true
    },
    {
      "linie": "S7",
      "ziel": "tzh",
      "plan": "",
      "dauer": 0,
      "zwischenhalte": [],
      "canceled": false,
      "date": "",
      "plannedDate": "",
      "_uniqueId": "train_lmy1e5vis_1770934297521",
      "projectId": "project_9ao8r6p2f_1770834514727",
      "type": "todo",
      "todoChecked": true
    },
    {
      "linie": "S7",
      "ziel": "jr",
      "plan": "",
      "dauer": 0,
      "zwischenhalte": [],
      "canceled": false,
      "date": "",
      "plannedDate": "",
      "_uniqueId": "train_g11z0fa24_1770934297800",
      "projectId": "project_9ao8r6p2f_1770834514727",
      "type": "todo",
      "todoChecked": true
    },
    {
      "linie": "S7",
      "ziel": "zj",
      "plan": "",
      "dauer": 0,
      "zwischenhalte": [],
      "canceled": false,
      "date": "",
      "plannedDate": "",
      "_uniqueId": "train_na0napc71_1770934298069",
      "projectId": "project_9ao8r6p2f_1770834514727",
      "type": "todo",
      "todoChecked": true
    },
    {
      "linie": "S7",
      "ziel": "m",
      "plan": "",
      "dauer": 0,
      "zwischenhalte": [],
      "canceled": false,
      "date": "",
      "plannedDate": "",
      "_uniqueId": "train_wgor7gy4d_1770934298355",
      "projectId": "project_9ao8r6p2f_1770834514727",
      "type": "todo",
      "todoChecked": false
    },
    {
      "linie": "S7",
      "ziel": "m",
      "plan": "",
      "dauer": 0,
      "zwischenhalte": [],
      "canceled": false,
      "date": "",
      "plannedDate": "",
      "_uniqueId": "train_2kysfh2rx_1770934298517",
      "projectId": "project_9ao8r6p2f_1770834514727",
      "type": "todo",
      "todoChecked": false
    },
    {
      "linie": "S7",
      "ziel": "nt",
      "plan": "",
      "dauer": 0,
      "zwischenhalte": [],
      "canceled": false,
      "date": "",
      "plannedDate": "",
      "_uniqueId": "train_2wa69l9jg_1770934298833",
      "projectId": "project_9ao8r6p2f_1770834514727",
      "type": "todo",
      "todoChecked": false
    },
    {
      "linie": "S7",
      "ziel": "mtzjmzku",
      "plan": "",
      "dauer": 0,
      "zwischenhalte": [],
      "canceled": false,
      "date": "",
      "plannedDate": "",
      "_uniqueId": "train_2t61hvfok_1770934299281",
      "projectId": "project_9ao8r6p2f_1770834514727",
      "type": "todo",
      "todoChecked": false
    },
    {
      "linie": "S7",
      "ziel": "zki",
      "plan": "",
      "dauer": 0,
      "zwischenhalte": [],
      "canceled": false,
      "date": "",
      "plannedDate": "",
      "_uniqueId": "train_i8rlbh2nm_1770934299476",
      "projectId": "project_9ao8r6p2f_1770834514727",
      "type": "todo",
      "todoChecked": false
    },
    {
      "linie": "S7",
      "ziel": "k",
      "plan": "",
      "dauer": 0,
      "zwischenhalte": [],
      "canceled": false,
      "date": "",
      "plannedDate": "",
      "_uniqueId": "train_huelt967r_1770934299630",
      "projectId": "project_9ao8r6p2f_1770834514727",
      "type": "todo",
      "todoChecked": false
    },
    {
      "linie": "S7",
      "ziel": "dgf",
      "plan": "",
      "dauer": 0,
      "zwischenhalte": [],
      "canceled": false,
      "date": "",
      "plannedDate": "",
      "_uniqueId": "train_aztgbeolw_1770934300284",
      "projectId": "project_9ao8r6p2f_1770834514727",
      "type": "todo",
      "todoChecked": false
    },
    {
      "linie": "NOTE",
      "type": "note",
      "name": "Neue Notiz",
      "ziel": "give it a name",
      "zwischenhalte": [
        "MY NAME IS PINK AND IM GLAD TO MEET YOU"
      ],
      "date": "2026-02-12",
      "_uniqueId": "note_1ssw8u2or_1770935475720",
      "plannedDate": "2026-02-12"
    },
    {
      "linie": "NOTE",
      "type": "note",
      "ziel": "gave you another chance",
      "zwischenhalte": [
        "fuck off"
      ],
      "date": "2026-02-12",
      "_uniqueId": "note_xm6shd2y4_1770936649162",
      "plannedDate": "2026-02-12"
    }
  ],
  "trains": [],
  "projects": [
    {
      "_uniqueId": "project_9ao8r6p2f_1770834514727",
      "name": "Dienstwagen - Bitte nicht einsteigen. Do not enter.Dienstwagen - Bitte nicht einsteigen. Do not enter.",
      "linie": "s7",
      "deadline": "2025-10-10T10:10",
      "createdAt": "2026-02-11T18:28:34.727Z",
      "tasks": [],
      "currentView": "todo",
      "completedExpanded": true,
      "completedSectionOpen": true
    },
    {
      "_uniqueId": "project_6oej3qm4n_1770914709412",
      "name": "FLURUS",
      "linie": "s5",
      "deadline": "",
      "createdAt": "2026-02-12T16:45:09.412Z",
      "tasks": [],
      "currentView": "todo"
    },
    {
      "_uniqueId": "project_h76rv00pj_1770920049959",
      "name": "",
      "linie": "s5",
      "deadline": null,
      "createdAt": "2026-02-12T18:14:09.959Z",
      "tasks": []
    },
    {
      "_uniqueId": "project_59yyaor0p_1771020721904",
      "name": "Lol",
      "linie": "s6",
      "deadline": "",
      "createdAt": "2026-02-13T22:12:01.904Z",
      "tasks": [],
      "currentView": "aufgabe"
    }
  ]
}